<?xml version="1.0" encoding="utf-8"?>
<StructureDefinition xmlns="http://hl7.org/fhir">
  <id value="sfm-reseptamendment" />
  <meta>
    <versionId value="10" />
    <lastUpdated value="2018-10-03T13:59:51.379+00:00" />
  </meta>
  <url value="http://ehelse.no/fhir/StructureDefinition/sfm-reseptamendment" />
  <version value="2.0" />
  <name value="SfmReseptamendment" />
  <title value="sfm-reseptamendment" />
  <status value="draft" />
  <date value="2019-09-15" />
  <description value="Information required in Norwegian e-resept (electronic prescription)." />
  <fhirVersion value="4.0.0" />
  <kind value="complex-type" />
  <abstract value="false" />
  <context>
    <type value="element" />
    <expression value="MedicationStatement" />
  </context>
  <context>
    <type value="element" />
    <expression value="Basic" />
  </context>
  <type value="Extension" />
  <baseDefinition value="http://hl7.org/fhir/StructureDefinition/Extension" />
  <derivation value="constraint" />
  <differential>
    <element id="Extension">
      <path value="Extension" />
      <short value="Norwegian resept information" />
      <definition value="Ifnormation that is relevant for Norwegian e-prescription." />
    </element>
    <element id="Extension.extension">
      <path value="Extension.extension" />
      <slicing>
        <discriminator>
          <type value="value" />
          <path value="url" />
        </discriminator>
        <rules value="open" />
      </slicing>
    </element>
    <element id="Extension.extension:reseptdate">
      <path value="Extension.extension" />
      <sliceName value="reseptdate" />
      <short value="Date the resept was signed" />
      <definition value="." />
      <min value="1" />
      <max value="1" />
    </element>
    <element id="Extension.extension:reseptdate.value[x]">
      <path value="Extension.extension.value[x]" />
      <slicing>
        <discriminator>
          <type value="type" />
          <path value="$this" />
        </discriminator>
        <rules value="closed" />
      </slicing>
    </element>
    <element id="Extension.extension:reseptdate.value[x]:valueDate">
      <path value="Extension.extension.value[x]" />
      <sliceName value="valueDate" />
      <type>
        <code value="date" />
      </type>
    </element>
    <element id="Extension.extension:expirationdate">
      <path value="Extension.extension" />
      <sliceName value="expirationdate" />
      <short value="Last date the pharmacy can deliver" />
      <definition value="." />
      <min value="1" />
      <max value="1" />
    </element>
    <element id="Extension.extension:expirationdate.value[x]">
      <path value="Extension.extension.value[x]" />
      <slicing>
        <discriminator>
          <type value="type" />
          <path value="$this" />
        </discriminator>
        <rules value="closed" />
      </slicing>
    </element>
    <element id="Extension.extension:expirationdate.value[x]:valueDate">
      <path value="Extension.extension.value[x]" />
      <sliceName value="valueDate" />
      <type>
        <code value="date" />
      </type>
    </element>
    <element id="Extension.extension:festUpdate">
      <path value="Extension.extension" />
      <sliceName value="festUpdate" />
      <short value="Version of FEST" />
      <definition value="." />
      <min value="1" />
      <max value="1" />
    </element>
    <element id="Extension.extension:festUpdate.value[x]">
      <path value="Extension.extension.value[x]" />
      <slicing>
        <discriminator>
          <type value="type" />
          <path value="$this" />
        </discriminator>
        <rules value="closed" />
      </slicing>
    </element>
    <element id="Extension.extension:festUpdate.value[x]:valueDateTime">
      <path value="Extension.extension.value[x]" />
      <sliceName value="valueDateTime" />
      <type>
        <code value="dateTime" />
      </type>
    </element>
    <element id="Extension.extension:conscription">
      <path value="Extension.extension" />
      <sliceName value="conscription" />
      <short value="Concriptive soldier" />
      <definition value="Boolean that identify if the patient is a soldier." />
      <max value="1" />
    </element>
    <element id="Extension.extension:conscription.value[x]">
      <path value="Extension.extension.value[x]" />
      <slicing>
        <discriminator>
          <type value="type" />
          <path value="$this" />
        </discriminator>
        <rules value="closed" />
      </slicing>
    </element>
    <element id="Extension.extension:conscription.value[x]:valueBoolean">
      <path value="Extension.extension.value[x]" />
      <sliceName value="valueBoolean" />
      <type>
        <code value="boolean" />
      </type>
    </element>
    <element id="Extension.extension:helfoapplication">
      <path value="Extension.extension" />
      <sliceName value="helfoapplication" />
      <short value="Individuel application to Helfo" />
      <definition value="Request to Helfo for medication cost refund" />
      <max value="1" />
    </element>
    <element id="Extension.extension:helfoapplication.value[x]">
      <path value="Extension.extension.value[x]" />
      <slicing>
        <discriminator>
          <type value="type" />
          <path value="$this" />
        </discriminator>
        <rules value="closed" />
      </slicing>
    </element>
    <element id="Extension.extension:helfoapplication.value[x]:valueBoolean">
      <path value="Extension.extension.value[x]" />
      <sliceName value="valueBoolean" />
      <type>
        <code value="boolean" />
      </type>
    </element>
    <element id="Extension.extension:freecard">
      <path value="Extension.extension" />
      <sliceName value="freecard" />
      <short value="Refund card" />
      <definition value="Registration that the patient get all expences refunded by the gouverment." />
      <max value="1" />
    </element>
    <element id="Extension.extension:freecard.value[x]">
      <path value="Extension.extension.value[x]" />
      <slicing>
        <discriminator>
          <type value="type" />
          <path value="$this" />
        </discriminator>
        <rules value="closed" />
      </slicing>
    </element>
    <element id="Extension.extension:freecard.value[x]:valueBoolean">
      <path value="Extension.extension.value[x]" />
      <sliceName value="valueBoolean" />
      <type>
        <code value="boolean" />
      </type>
    </element>
    <element id="Extension.extension:guardiantransparencyreservation">
      <path value="Extension.extension" />
      <sliceName value="guardiantransparencyreservation" />
      <short value="Guardian transperecy reservation" />
      <definition value="boolean that states that the patients guardian should not have access to the resept." />
      <max value="1" />
    </element>
    <element id="Extension.extension:guardiantransparencyreservation.value[x]">
      <path value="Extension.extension.value[x]" />
      <slicing>
        <discriminator>
          <type value="type" />
          <path value="$this" />
        </discriminator>
        <rules value="closed" />
      </slicing>
    </element>
    <element id="Extension.extension:guardiantransparencyreservation.value[x]:valueBoolean">
      <path value="Extension.extension.value[x]" />
      <sliceName value="valueBoolean" />
      <type>
        <code value="boolean" />
      </type>
    </element>
    <element id="Extension.extension:ownpractice">
      <path value="Extension.extension" />
      <sliceName value="ownpractice" />
      <short value="Identify that the medication is for use in own organisation" />
      <definition value="." />
      <max value="1" />
    </element>
    <element id="Extension.extension:ownpractice.value[x]">
      <path value="Extension.extension.value[x]" />
      <slicing>
        <discriminator>
          <type value="type" />
          <path value="$this" />
        </discriminator>
        <rules value="closed" />
      </slicing>
    </element>
    <element id="Extension.extension:ownpractice.value[x]:valueBoolean">
      <path value="Extension.extension.value[x]" />
      <sliceName value="valueBoolean" />
      <type>
        <code value="boolean" />
      </type>
    </element>
    <element id="Extension.extension:indoctorsname">
      <path value="Extension.extension" />
      <sliceName value="indoctorsname" />
      <short value="Resept in doctors name" />
      <definition value="mechansims to keep the patient name secret to the pharmacy." />
      <max value="1" />
    </element>
    <element id="Extension.extension:indoctorsname.value[x]">
      <path value="Extension.extension.value[x]" />
      <slicing>
        <discriminator>
          <type value="type" />
          <path value="$this" />
        </discriminator>
        <rules value="closed" />
      </slicing>
    </element>
    <element id="Extension.extension:indoctorsname.value[x]:valueBoolean">
      <path value="Extension.extension.value[x]" />
      <sliceName value="valueBoolean" />
      <type>
        <code value="boolean" />
      </type>
    </element>
    <element id="Extension.extension:refnum">
      <path value="Extension.extension" />
      <sliceName value="refnum" />
      <short value="Reference number" />
      <definition value="Used when the resept is locked or when patient do not have norwegian legal identity." />
      <max value="1" />
    </element>
    <element id="Extension.extension:refnum.value[x]">
      <path value="Extension.extension.value[x]" />
      <slicing>
        <discriminator>
          <type value="type" />
          <path value="$this" />
        </discriminator>
        <rules value="closed" />
      </slicing>
    </element>
    <element id="Extension.extension:refnum.value[x]:valueString">
      <path value="Extension.extension.value[x]" />
      <sliceName value="valueString" />
      <type>
        <code value="string" />
      </type>
    </element>
    <element id="Extension.extension:speciality">
      <path value="Extension.extension" />
      <sliceName value="speciality" />
      <short value="Speciality" />
      <definition value="Speciality that the doctor hold." />
    </element>
    <element id="Extension.extension:speciality.value[x]">
      <path value="Extension.extension.value[x]" />
      <slicing>
        <discriminator>
          <type value="type" />
          <path value="$this" />
        </discriminator>
        <rules value="closed" />
      </slicing>
    </element>
    <element id="Extension.extension:speciality.value[x]:valueCodeableConcept">
      <path value="Extension.extension.value[x]" />
      <sliceName value="valueCodeableConcept" />
      <type>
        <code value="CodeableConcept" />
      </type>
    </element>
    <element id="Extension.extension:speciality.value[x]:valueCodeableConcept.coding.system">
      <path value="Extension.extension.value[x].coding.system" />
      <fixedUri value="urn:uid:2.16.578.1.12.4.1.1.7428" />
    </element>
    <element id="Extension.extension:dispatchrequest">
      <path value="Extension.extension" />
      <sliceName value="dispatchrequest" />
      <short value="Request for delivery to patient" />
      <definition value="Request to a single pharmacy to prepare (or send) the medication to the patient." />
      <max value="1" />
    </element>
    <element id="Extension.extension:dispatchrequest.extension">
      <path value="Extension.extension.extension" />
      <slicing>
        <discriminator>
          <type value="value" />
          <path value="url" />
        </discriminator>
        <rules value="open" />
      </slicing>
    </element>
    <element id="Extension.extension:dispatchrequest.extension:condition">
      <path value="Extension.extension.extension" />
      <sliceName value="condition" />
      <min value="1" />
      <max value="1" />
    </element>
    <element id="Extension.extension:dispatchrequest.extension:condition.value[x]">
      <path value="Extension.extension.extension.value[x]" />
      <slicing>
        <discriminator>
          <type value="type" />
          <path value="$this" />
        </discriminator>
        <rules value="closed" />
      </slicing>
    </element>
    <element id="Extension.extension:dispatchrequest.extension:condition.value[x]:valueBoolean">
      <path value="Extension.extension.extension.value[x]" />
      <sliceName value="valueBoolean" />
      <type>
        <code value="boolean" />
      </type>
    </element>
    <element id="Extension.extension:dispatchrequest.extension:metod">
      <path value="Extension.extension.extension" />
      <sliceName value="metod" />
      <min value="1" />
      <max value="1" />
    </element>
    <element id="Extension.extension:dispatchrequest.extension:metod.value[x]">
      <path value="Extension.extension.extension.value[x]" />
      <slicing>
        <discriminator>
          <type value="type" />
          <path value="$this" />
        </discriminator>
        <rules value="closed" />
      </slicing>
    </element>
    <element id="Extension.extension:dispatchrequest.extension:metod.value[x]:valueCodeableConcept">
      <path value="Extension.extension.extension.value[x]" />
      <sliceName value="valueCodeableConcept" />
      <type>
        <code value="CodeableConcept" />
      </type>
    </element>
    <element id="Extension.extension:dispatchrequest.extension:metod.value[x]:valueCodeableConcept.coding.system">
      <path value="Extension.extension.extension.value[x].coding.system" />
      <fixedUri value="urn:uid:2.16.578.1.12.4.1.1.7404" />
    </element>
    <element id="Extension.extension:dispatchrequest.extension:metod.value[x]:valueCodeableConcept.coding.code">
      <path value="Extension.extension.extension.value[x].coding.code" />
      <min value="1" />
    </element>
    <element id="Extension.extension:dispatchrequest.extension:metod.value[x]:valueCodeableConcept.coding.display">
      <path value="Extension.extension.extension.value[x].coding.display" />
      <min value="1" />
    </element>
    <element id="Extension.extension:dispatchrequest.extension:organization">
      <path value="Extension.extension.extension" />
      <sliceName value="organization" />
      <min value="1" />
      <max value="1" />
    </element>
    <element id="Extension.extension:dispatchrequest.extension:organization.value[x]">
      <path value="Extension.extension.extension.value[x]" />
      <slicing>
        <discriminator>
          <type value="type" />
          <path value="$this" />
        </discriminator>
        <rules value="closed" />
      </slicing>
    </element>
    <element id="Extension.extension:dispatchrequest.extension:organization.value[x]:valueString">
      <path value="Extension.extension.extension.value[x]" />
      <sliceName value="valueString" />
      <type>
        <code value="string" />
      </type>
    </element>
    <element id="Extension.extension:dispatchrequest.extension:contactperson">
      <path value="Extension.extension.extension" />
      <sliceName value="contactperson" />
      <min value="1" />
      <max value="1" />
    </element>
    <element id="Extension.extension:dispatchrequest.extension:contactperson.value[x]">
      <path value="Extension.extension.extension.value[x]" />
      <slicing>
        <discriminator>
          <type value="type" />
          <path value="$this" />
        </discriminator>
        <rules value="closed" />
      </slicing>
    </element>
    <element id="Extension.extension:dispatchrequest.extension:contactperson.value[x]:valueString">
      <path value="Extension.extension.extension.value[x]" />
      <sliceName value="valueString" />
      <type>
        <code value="string" />
      </type>
    </element>
    <element id="Extension.extension:dispatchrequest.extension:note">
      <path value="Extension.extension.extension" />
      <sliceName value="note" />
      <max value="1" />
    </element>
    <element id="Extension.extension:dispatchrequest.extension:note.value[x]">
      <path value="Extension.extension.extension.value[x]" />
      <slicing>
        <discriminator>
          <type value="type" />
          <path value="$this" />
        </discriminator>
        <rules value="closed" />
      </slicing>
    </element>
    <element id="Extension.extension:dispatchrequest.extension:note.value[x]:valueString">
      <path value="Extension.extension.extension.value[x]" />
      <sliceName value="valueString" />
      <type>
        <code value="string" />
      </type>
    </element>
    <element id="Extension.extension:dispatchrequest.extension:orgnum">
      <path value="Extension.extension.extension" />
      <sliceName value="orgnum" />
      <min value="1" />
      <max value="1" />
    </element>
    <element id="Extension.extension:dispatchrequest.extension:orgnum.value[x]">
      <path value="Extension.extension.extension.value[x]" />
      <slicing>
        <discriminator>
          <type value="type" />
          <path value="$this" />
        </discriminator>
        <rules value="closed" />
      </slicing>
    </element>
    <element id="Extension.extension:dispatchrequest.extension:orgnum.value[x]:valueString">
      <path value="Extension.extension.extension.value[x]" />
      <sliceName value="valueString" />
      <type>
        <code value="string" />
      </type>
    </element>
    <element id="Extension.extension:dispatchrequest.extension:orgname">
      <path value="Extension.extension.extension" />
      <sliceName value="orgname" />
      <min value="1" />
      <max value="1" />
    </element>
    <element id="Extension.extension:dispatchrequest.extension:orgname.value[x]">
      <path value="Extension.extension.extension.value[x]" />
      <slicing>
        <discriminator>
          <type value="type" />
          <path value="$this" />
        </discriminator>
        <rules value="closed" />
      </slicing>
    </element>
    <element id="Extension.extension:dispatchrequest.extension:orgname.value[x]:valueString">
      <path value="Extension.extension.extension.value[x]" />
      <sliceName value="valueString" />
      <type>
        <code value="string" />
      </type>
    </element>
    <element id="Extension.extension:dispatchrequest.extension:address">
      <path value="Extension.extension.extension" />
      <sliceName value="address" />
      <max value="1" />
    </element>
    <element id="Extension.extension:dispatchrequest.extension:address.value[x]">
      <path value="Extension.extension.extension.value[x]" />
      <slicing>
        <discriminator>
          <type value="type" />
          <path value="$this" />
        </discriminator>
        <rules value="closed" />
      </slicing>
    </element>
    <element id="Extension.extension:dispatchrequest.extension:address.value[x]:valueReference">
      <path value="Extension.extension.extension.value[x]" />
      <sliceName value="valueReference" />
      <type>
        <code value="Reference" />
        <targetProfile value="http://hl7.no/fhir/StructureDefinition/no-basis-Address" />
        <aggregation value="bundled" />
      </type>
    </element>
    <element id="Extension.extension:dispatchrequest.value[x]">
      <path value="Extension.extension.value[x]" />
      <max value="0" />
    </element>
    <element id="Extension.extension:earliestdispence">
      <path value="Extension.extension" />
      <sliceName value="earliestdispence" />
      <short value="Earliest delivery" />
      <definition value="The first date the doctor want the pharmacy to deliver the medication to the patient." />
      <max value="1" />
    </element>
    <element id="Extension.extension:earliestdispence.value[x]">
      <path value="Extension.extension.value[x]" />
      <slicing>
        <discriminator>
          <type value="type" />
          <path value="$this" />
        </discriminator>
        <rules value="closed" />
      </slicing>
    </element>
    <element id="Extension.extension:earliestdispence.value[x]:valueDate">
      <path value="Extension.extension.value[x]" />
      <sliceName value="valueDate" />
      <type>
        <code value="date" />
      </type>
    </element>
    <element id="Extension.extension:dischargedhospital">
      <path value="Extension.extension" />
      <sliceName value="dischargedhospital" />
      <short value="Discharged from hosptital" />
      <definition value="." />
      <max value="1" />
    </element>
    <element id="Extension.extension:dischargedhospital.value[x]">
      <path value="Extension.extension.value[x]" />
      <slicing>
        <discriminator>
          <type value="type" />
          <path value="$this" />
        </discriminator>
        <rules value="closed" />
      </slicing>
    </element>
    <element id="Extension.extension:dischargedhospital.value[x]:valueBoolean">
      <path value="Extension.extension.value[x]" />
      <sliceName value="valueBoolean" />
      <type>
        <code value="boolean" />
      </type>
    </element>
    <element id="Extension.extension:lockedresept">
      <path value="Extension.extension" />
      <sliceName value="lockedresept" />
      <short value="Locked resept" />
      <definition value="." />
      <max value="1" />
    </element>
    <element id="Extension.extension:lockedresept.value[x]">
      <path value="Extension.extension.value[x]" />
      <slicing>
        <discriminator>
          <type value="type" />
          <path value="$this" />
        </discriminator>
        <rules value="closed" />
      </slicing>
    </element>
    <element id="Extension.extension:lockedresept.value[x]:valueBoolean">
      <path value="Extension.extension.value[x]" />
      <sliceName value="valueBoolean" />
      <type>
        <code value="boolean" />
      </type>
    </element>
    <element id="Extension.extension:itemgroup">
      <path value="Extension.extension" />
      <sliceName value="itemgroup" />
      <short value="Type of resept" />
      <definition value="Identify what type of resept it is. Medication, Nutrition support etc." />
      <min value="1" />
      <max value="1" />
    </element>
    <element id="Extension.extension:itemgroup.value[x]">
      <path value="Extension.extension.value[x]" />
      <slicing>
        <discriminator>
          <type value="type" />
          <path value="$this" />
        </discriminator>
        <rules value="closed" />
      </slicing>
    </element>
    <element id="Extension.extension:itemgroup.value[x]:valueCodeableConcept">
      <path value="Extension.extension.value[x]" />
      <sliceName value="valueCodeableConcept" />
      <type>
        <code value="CodeableConcept" />
      </type>
    </element>
    <element id="Extension.extension:itemgroup.value[x]:valueCodeableConcept.coding.system">
      <path value="Extension.extension.value[x].coding.system" />
      <fixedUri value="urn:uid:2.16.578.1.12.4.1.1.7402" />
    </element>
    <element id="Extension.extension:numberofpackages">
      <path value="Extension.extension" />
      <sliceName value="numberofpackages" />
      <short value="Number of packages" />
      <definition value="." />
      <max value="1" />
    </element>
    <element id="Extension.extension:numberofpackages.value[x]">
      <path value="Extension.extension.value[x]" />
      <slicing>
        <discriminator>
          <type value="type" />
          <path value="$this" />
        </discriminator>
        <rules value="closed" />
      </slicing>
    </element>
    <element id="Extension.extension:numberofpackages.value[x]:valueDecimal">
      <path value="Extension.extension.value[x]" />
      <sliceName value="valueDecimal" />
      <type>
        <code value="decimal" />
      </type>
    </element>
    <element id="Extension.extension:reimbursmentparagraph">
      <path value="Extension.extension" />
      <sliceName value="reimbursmentparagraph" />
      <short value="Refund paragraph" />
      <definition value="." />
      <max value="1" />
    </element>
    <element id="Extension.extension:reimbursmentparagraph.value[x]">
      <path value="Extension.extension.value[x]" />
      <slicing>
        <discriminator>
          <type value="type" />
          <path value="$this" />
        </discriminator>
        <rules value="closed" />
      </slicing>
    </element>
    <element id="Extension.extension:reimbursmentparagraph.value[x]:valueCodeableConcept">
      <path value="Extension.extension.value[x]" />
      <sliceName value="valueCodeableConcept" />
      <type>
        <code value="CodeableConcept" />
      </type>
    </element>
    <element id="Extension.extension:reimbursmentparagraph.value[x]:valueCodeableConcept.coding.system">
      <path value="Extension.extension.value[x].coding.system" />
      <min value="1" />
      <fixedUri value="urn:uid:2.16.578.1.12.4.1.1.7427" />
    </element>
    <element id="Extension.extension:reimbursmentparagraph.value[x]:valueCodeableConcept.coding.code">
      <path value="Extension.extension.value[x].coding.code" />
      <min value="1" />
    </element>
    <element id="Extension.extension:reimbursmentparagraph.value[x]:valueCodeableConcept.coding.display">
      <path value="Extension.extension.value[x].coding.display" />
      <min value="1" />
    </element>
    <element id="Extension.extension:reimbursementcode">
      <path value="Extension.extension" />
      <sliceName value="reimbursementcode" />
      <short value="Refund code" />
      <definition value=".Accepted coding systems: 7110, 7170, 7434, 7435." />
      <max value="1" />
    </element>
    <element id="Extension.extension:reimbursementcode.value[x]">
      <path value="Extension.extension.value[x]" />
      <slicing>
        <discriminator>
          <type value="type" />
          <path value="$this" />
        </discriminator>
        <rules value="closed" />
      </slicing>
    </element>
    <element id="Extension.extension:reimbursementcode.value[x]:valueCodeableConcept">
      <path value="Extension.extension.value[x]" />
      <sliceName value="valueCodeableConcept" />
      <type>
        <code value="CodeableConcept" />
      </type>
    </element>
    <element id="Extension.extension:reimbursementcode.value[x]:valueCodeableConcept.coding.system">
      <path value="Extension.extension.value[x].coding.system" />
      <min value="1" />
    </element>
    <element id="Extension.extension:reimbursementcode.value[x]:valueCodeableConcept.coding.code">
      <path value="Extension.extension.value[x].coding.code" />
      <min value="1" />
    </element>
    <element id="Extension.extension:reimbursementcode.value[x]:valueCodeableConcept.coding.display">
      <path value="Extension.extension.value[x].coding.display" />
      <min value="1" />
    </element>
    <element id="Extension.extension:plomedicationmanagement">
      <path value="Extension.extension" />
      <sliceName value="plomedicationmanagement" />
      <short value="Patient treated by the municipal" />
      <definition value="." />
      <max value="1" />
    </element>
    <element id="Extension.extension:plomedicationmanagement.value[x]">
      <path value="Extension.extension.value[x]" />
      <slicing>
        <discriminator>
          <type value="type" />
          <path value="$this" />
        </discriminator>
        <rules value="closed" />
      </slicing>
    </element>
    <element id="Extension.extension:plomedicationmanagement.value[x]:valueString">
      <path value="Extension.extension.value[x]" />
      <sliceName value="valueString" />
      <type>
        <code value="string" />
      </type>
    </element>
    <element id="Extension.extension:reit">
      <path value="Extension.extension" />
      <sliceName value="reit" />
      <short value="Number of deliveries" />
      <definition value="." />
      <min value="1" />
      <max value="1" />
    </element>
    <element id="Extension.extension:reit.value[x]">
      <path value="Extension.extension.value[x]" />
      <slicing>
        <discriminator>
          <type value="type" />
          <path value="$this" />
        </discriminator>
        <rules value="closed" />
      </slicing>
    </element>
    <element id="Extension.extension:reit.value[x]:valueInteger">
      <path value="Extension.extension.value[x]" />
      <sliceName value="valueInteger" />
      <type>
        <code value="integer" />
      </type>
    </element>
    <element id="Extension.extension:amount">
      <path value="Extension.extension" />
      <sliceName value="amount" />
      <short value="Amount of drug prescribed" />
      <definition value="identifies the number of tablets or amount of liquid that should be delivered to the patient for each REIT." />
      <max value="1" />
    </element>
    <element id="Extension.extension:amount.value[x]">
      <path value="Extension.extension.value[x]" />
      <slicing>
        <discriminator>
          <type value="type" />
          <path value="$this" />
        </discriminator>
        <rules value="closed" />
      </slicing>
    </element>
    <element id="Extension.extension:amount.value[x]:valueQuantity">
      <path value="Extension.extension.valueQuantity" />
      <sliceName value="valueQuantity" />
      <type>
        <code value="Quantity" />
        <profile value="http://hl7.org/fhir/StructureDefinition/SimpleQuantity" />
      </type>
    </element>
    <element id="Extension.extension:amount.value[x]:valueQuantity.value">
      <path value="Extension.extension.valueQuantity.value" />
      <min value="1" />
    </element>
    <element id="Extension.extension:amount.value[x]:valueQuantity.system">
      <path value="Extension.extension.valueQuantity.system" />
      <min value="1" />
      <fixedUri value="urn:uid:2.16.578.1.12.4.1.1.7452" />
    </element>
    <element id="Extension.extension:amount.value[x]:valueQuantity.code">
      <path value="Extension.extension.valueQuantity.code" />
      <min value="1" />
    </element>
    <element id="Extension.extension:dssn">
      <path value="Extension.extension" />
      <sliceName value="dssn" />
      <max value="1" />
    </element>
    <element id="Extension.extension:dssn.value[x]">
      <path value="Extension.extension.value[x]" />
      <slicing>
        <discriminator>
          <type value="type" />
          <path value="$this" />
        </discriminator>
        <rules value="closed" />
      </slicing>
    </element>
    <element id="Extension.extension:dssn.value[x]:valueString">
      <path value="Extension.extension.value[x]" />
      <sliceName value="valueString" />
      <type>
        <code value="string" />
      </type>
    </element>
    <element id="Extension.extension:rfstatus">
      <path value="Extension.extension" />
      <sliceName value="rfstatus" />
      <short value="Identifies if in RF and status in RF" />
      <max value="1" />
    </element>
    <element id="Extension.extension:rfstatus.value[x]">
      <path value="Extension.extension.value[x]" />
      <slicing>
        <discriminator>
          <type value="type" />
          <path value="$this" />
        </discriminator>
        <rules value="closed" />
      </slicing>
    </element>
    <element id="Extension.extension:rfstatus.value[x]:valueCodeableConcept">
      <path value="Extension.extension.value[x]" />
      <sliceName value="valueCodeableConcept" />
      <type>
        <code value="CodeableConcept" />
      </type>
    </element>
    <element id="Extension.extension:rfstatus.value[x]:valueCodeableConcept.coding.system">
      <path value="Extension.extension.value[x].coding.system" />
      <fixedUri value="urn:uid:2.16.578.1.12.4.1.1.7408" />
    </element>
    <element id="Extension.extension:note">
      <path value="Extension.extension" />
      <sliceName value="note" />
      <short value="Note from prescriber to pharmacy" />
      <definition value="Textual information that prescriber has provided for the pharmacy, in order to support the dispence." />
      <max value="1" />
    </element>
    <element id="Extension.extension:note.value[x]">
      <path value="Extension.extension.value[x]" />
      <slicing>
        <discriminator>
          <type value="type" />
          <path value="$this" />
        </discriminator>
        <rules value="closed" />
      </slicing>
    </element>
    <element id="Extension.extension:note.value[x]:valueString">
      <path value="Extension.extension.value[x]" />
      <sliceName value="valueString" />
      <type>
        <code value="string" />
      </type>
    </element>
    <element id="Extension.extension:dispencesummary">
      <path value="Extension.extension" />
      <sliceName value="dispencesummary" />
      <short value="Delivery summary from RF" />
      <definition value="Information provided from RF. Summary of what has been dispenced on the prescription (resept)." />
    </element>
    <element id="Extension.extension:dispencesummary.extension">
      <path value="Extension.extension.extension" />
      <slicing>
        <discriminator>
          <type value="value" />
          <path value="url" />
        </discriminator>
        <rules value="open" />
      </slicing>
    </element>
    <element id="Extension.extension:dispencesummary.extension:varenummer">
      <path value="Extension.extension.extension" />
      <sliceName value="varenummer" />
      <max value="1" />
    </element>
    <element id="Extension.extension:dispencesummary.extension:varenummer.url">
      <path value="Extension.extension.extension.url" />
      <fixedString value="varenummer" />
    </element>
    <element id="Extension.extension:dispencesummary.extension:varenummer.value[x]">
      <path value="Extension.extension.extension.value[x]" />
      <type>
        <code value="string" />
      </type>
    </element>
    <element id="Extension.extension:dispencesummary.extension:nameformstrenght">
      <path value="Extension.extension.extension" />
      <sliceName value="nameformstrenght" />
      <min value="1" />
      <max value="1" />
    </element>
    <element id="Extension.extension:dispencesummary.extension:nameformstrenght.url">
      <path value="Extension.extension.extension.url" />
      <fixedString value="nameformstrenght" />
    </element>
    <element id="Extension.extension:dispencesummary.extension:nameformstrenght.value[x]">
      <path value="Extension.extension.extension.value[x]" />
      <type>
        <code value="string" />
      </type>
    </element>
    <element id="Extension.extension:dispencesummary.extension:packingsize">
      <path value="Extension.extension.extension" />
      <sliceName value="packingsize" />
      <max value="1" />
    </element>
    <element id="Extension.extension:dispencesummary.extension:packingsize.url">
      <path value="Extension.extension.extension.url" />
      <fixedString value="packingsize" />
    </element>
    <element id="Extension.extension:dispencesummary.extension:packingsize.value[x]">
      <path value="Extension.extension.extension.value[x]" />
      <type>
        <code value="Quantity" />
      </type>
    </element>
    <element id="Extension.extension:dispencesummary.extension:noPackingTotal">
      <path value="Extension.extension.extension" />
      <sliceName value="noPackingTotal" />
      <min value="1" />
      <max value="1" />
    </element>
    <element id="Extension.extension:dispencesummary.extension:noPackingTotal.url">
      <path value="Extension.extension.extension.url" />
      <fixedString value="noPackingTotal" />
    </element>
    <element id="Extension.extension:dispencesummary.extension:noPackingTotal.value[x]">
      <path value="Extension.extension.extension.value[x]" />
      <type>
        <code value="decimal" />
      </type>
    </element>
    <element id="Extension.extension:dispencesummary.extension:noPackingLast">
      <path value="Extension.extension.extension" />
      <sliceName value="noPackingLast" />
      <min value="1" />
      <max value="1" />
    </element>
    <element id="Extension.extension:dispencesummary.extension:noPackingLast.url">
      <path value="Extension.extension.extension.url" />
      <fixedString value="noPackingLast" />
    </element>
    <element id="Extension.extension:dispencesummary.extension:noPackingLast.value[x]">
      <path value="Extension.extension.extension.value[x]" />
      <type>
        <code value="decimal" />
      </type>
    </element>
    <element id="Extension.extension:dispencesummary.extension:lastdeliverydate">
      <path value="Extension.extension.extension" />
      <sliceName value="lastdeliverydate" />
      <min value="1" />
      <max value="1" />
    </element>
    <element id="Extension.extension:dispencesummary.extension:lastdeliverydate.url">
      <path value="Extension.extension.extension.url" />
      <fixedString value="lastdeliverydate" />
    </element>
    <element id="Extension.extension:dispencesummary.extension:lastdeliverydate.value[x]">
      <path value="Extension.extension.extension.value[x]" />
      <type>
        <code value="dateTime" />
      </type>
    </element>
    <element id="Extension.extension:dispencesummary.url">
      <path value="Extension.extension.url" />
      <fixedString value="dispencesummary" />
    </element>
    <element id="Extension.extension:dispencesummary.value[x]">
      <path value="Extension.extension.value[x]" />
      <max value="0" />
    </element>
    <element id="Extension.extension:statusaction">
      <path value="Extension.extension" />
      <sliceName value="statusaction" />
      <short value="Action information for SFM" />
      <definition value="Instruction from EPJ to SFM regarding what should be done about prescription (resept)." />
      <max value="1" />
    </element>
    <element id="Extension.extension:statusaction.extension">
      <path value="Extension.extension.extension" />
      <slicing>
        <discriminator>
          <type value="value" />
          <path value="url" />
        </discriminator>
        <rules value="open" />
      </slicing>
    </element>
    <element id="Extension.extension:statusaction.extension:recallId">
      <path value="Extension.extension.extension" />
      <sliceName value="recallId" />
      <max value="1" />
    </element>
    <element id="Extension.extension:statusaction.extension:recallId.url">
      <path value="Extension.extension.extension.url" />
      <fixedString value="recallId" />
    </element>
    <element id="Extension.extension:statusaction.extension:recallId.value[x]">
      <path value="Extension.extension.extension.value[x]" />
      <type>
        <code value="string" />
      </type>
    </element>
    <element id="Extension.extension:statusaction.extension:text">
      <path value="Extension.extension.extension" />
      <sliceName value="text" />
      <max value="1" />
    </element>
    <element id="Extension.extension:statusaction.extension:text.url">
      <path value="Extension.extension.extension.url" />
      <fixedString value="text" />
    </element>
    <element id="Extension.extension:statusaction.extension:text.value[x]">
      <path value="Extension.extension.extension.value[x]" />
      <type>
        <code value="string" />
      </type>
    </element>
    <element id="Extension.extension:statusaction.extension:recallcode">
      <path value="Extension.extension.extension" />
      <sliceName value="recallcode" />
      <min value="1" />
      <max value="1" />
    </element>
    <element id="Extension.extension:statusaction.extension:recallcode.url">
      <path value="Extension.extension.extension.url" />
      <fixedString value="recallcode" />
    </element>
    <element id="Extension.extension:statusaction.extension:recallcode.value[x]">
      <path value="Extension.extension.extension.value[x]" />
      <slicing>
        <discriminator>
          <type value="type" />
          <path value="$this" />
        </discriminator>
        <rules value="closed" />
      </slicing>
      <type>
        <code value="CodeableConcept" />
      </type>
    </element>
    <element id="Extension.extension:statusaction.extension:recallcode.value[x]:valueCodeableConcept">
      <path value="Extension.extension.extension.value[x]" />
      <sliceName value="valueCodeableConcept" />
      <type>
        <code value="CodeableConcept" />
      </type>
    </element>
    <element id="Extension.extension:statusaction.extension:recallcode.value[x]:valueCodeableConcept.coding.system">
      <path value="Extension.extension.extension.value[x].coding.system" />
      <fixedUri value="urn:oid:2.16.578.1.12.4.1.1.7500" />
    </element>
    <element id="Extension.extension:statusaction.url">
      <path value="Extension.extension.url" />
      <fixedString value="statusaction" />
    </element>
    <element id="Extension.extension:statusaction.value[x]">
      <path value="Extension.extension.value[x]" />
      <max value="0" />
    </element>
    <element id="Extension.extension:ereseptdosing">
      <path value="Extension.extension" />
      <sliceName value="ereseptdosing" />
    </element>
    <element id="Extension.extension:ereseptdosing.extension">
      <path value="Extension.extension.extension" />
      <slicing>
        <discriminator>
          <type value="value" />
          <path value="url" />
        </discriminator>
        <rules value="open" />
      </slicing>
    </element>
    <element id="Extension.extension:ereseptdosing.extension:starttime">
      <path value="Extension.extension.extension" />
      <sliceName value="starttime" />
      <max value="1" />
    </element>
    <element id="Extension.extension:ereseptdosing.extension:starttime.url">
      <path value="Extension.extension.extension.url" />
      <fixedString value="starttime" />
    </element>
    <element id="Extension.extension:ereseptdosing.extension:endtime">
      <path value="Extension.extension.extension" />
      <sliceName value="endtime" />
      <max value="1" />
    </element>
    <element id="Extension.extension:ereseptdosing.extension:endtime.url">
      <path value="Extension.extension.extension.url" />
      <fixedString value="endtime" />
    </element>
    <element id="Extension.extension:ereseptdosing.extension:dosingrule">
      <path value="Extension.extension.extension" />
      <sliceName value="dosingrule" />
      <max value="1" />
    </element>
    <element id="Extension.extension:ereseptdosing.extension:dosingrule.extension">
      <path value="Extension.extension.extension.extension" />
      <slicing>
        <discriminator>
          <type value="value" />
          <path value="url" />
        </discriminator>
        <rules value="open" />
      </slicing>
    </element>
    <element id="Extension.extension:ereseptdosing.extension:dosingrule.extension:dosebasedon">
      <path value="Extension.extension.extension.extension" />
      <sliceName value="dosebasedon" />
      <min value="1" />
      <max value="1" />
    </element>
    <element id="Extension.extension:ereseptdosing.extension:dosingrule.extension:dosebasedon.url">
      <path value="Extension.extension.extension.extension.url" />
      <fixedString value="dosebasedon" />
    </element>
    <element id="Extension.extension:ereseptdosing.extension:dosingrule.extension:text">
      <path value="Extension.extension.extension.extension" />
      <sliceName value="text" />
      <max value="1" />
    </element>
    <element id="Extension.extension:ereseptdosing.extension:dosingrule.extension:text.url">
      <path value="Extension.extension.extension.extension.url" />
      <fixedString value="text" />
    </element>
    <element id="Extension.extension:ereseptdosing.extension:dosingrule.url">
      <path value="Extension.extension.extension.url" />
      <fixedString value="dosingrule" />
    </element>
    <element id="Extension.extension:ereseptdosing.extension:dosingrule.value[x]">
      <path value="Extension.extension.extension.value[x]" />
      <max value="0" />
    </element>
    <element id="Extension.extension:ereseptdosing.extension:repeatingdosage">
      <path value="Extension.extension.extension" />
      <sliceName value="repeatingdosage" />
      <min value="1" />
    </element>
    <element id="Extension.extension:ereseptdosing.extension:repeatingdosage.extension">
      <path value="Extension.extension.extension.extension" />
      <slicing>
        <discriminator>
          <type value="value" />
          <path value="url" />
        </discriminator>
        <rules value="open" />
      </slicing>
    </element>
    <element id="Extension.extension:ereseptdosing.extension:repeatingdosage.extension:amount">
      <path value="Extension.extension.extension.extension" />
      <sliceName value="amount" />
      <min value="1" />
      <max value="1" />
    </element>
    <element id="Extension.extension:ereseptdosing.extension:repeatingdosage.extension:amount.url">
      <path value="Extension.extension.extension.extension.url" />
      <fixedString value="amount" />
    </element>
    <element id="Extension.extension:ereseptdosing.extension:repeatingdosage.extension:interval">
      <path value="Extension.extension.extension.extension" />
      <sliceName value="interval" />
      <max value="1" />
    </element>
    <element id="Extension.extension:ereseptdosing.extension:repeatingdosage.extension:interval.url">
      <path value="Extension.extension.extension.extension.url" />
      <fixedString value="interval" />
    </element>
    <element id="Extension.extension:ereseptdosing.extension:repeatingdosage.extension:infusionspeed">
      <path value="Extension.extension.extension.extension" />
      <sliceName value="infusionspeed" />
      <max value="1" />
    </element>
    <element id="Extension.extension:ereseptdosing.extension:repeatingdosage.extension:infusionspeed.extension">
      <path value="Extension.extension.extension.extension.extension" />
      <slicing>
        <discriminator>
          <type value="value" />
          <path value="url" />
        </discriminator>
        <rules value="open" />
      </slicing>
    </element>
    <element id="Extension.extension:ereseptdosing.extension:repeatingdosage.extension:infusionspeed.extension:volum">
      <path value="Extension.extension.extension.extension.extension" />
      <sliceName value="volum" />
      <min value="1" />
      <max value="1" />
    </element>
    <element id="Extension.extension:ereseptdosing.extension:repeatingdosage.extension:infusionspeed.extension:volum.url">
      <path value="Extension.extension.extension.extension.extension.url" />
      <fixedString value="volum" />
    </element>
    <element id="Extension.extension:ereseptdosing.extension:repeatingdosage.extension:infusionspeed.extension:timeunit">
      <path value="Extension.extension.extension.extension.extension" />
      <sliceName value="timeunit" />
      <min value="1" />
      <max value="1" />
    </element>
    <element id="Extension.extension:ereseptdosing.extension:repeatingdosage.extension:infusionspeed.extension:timeunit.url">
      <path value="Extension.extension.extension.extension.extension.url" />
      <fixedString value="timeunit" />
    </element>
    <element id="Extension.extension:ereseptdosing.extension:repeatingdosage.extension:infusionspeed.url">
      <path value="Extension.extension.extension.extension.url" />
      <fixedString value="infusionspeed" />
    </element>
    <element id="Extension.extension:ereseptdosing.extension:repeatingdosage.extension:infusionspeed.value[x]">
      <path value="Extension.extension.extension.extension.value[x]" />
      <max value="0" />
    </element>
    <element id="Extension.extension:ereseptdosing.extension:repeatingdosage.extension:time">
      <path value="Extension.extension.extension.extension" />
      <sliceName value="time" />
      <max value="1" />
    </element>
    <element id="Extension.extension:ereseptdosing.extension:repeatingdosage.extension:time.url">
      <path value="Extension.extension.extension.extension.url" />
      <fixedString value="time" />
    </element>
    <element id="Extension.extension:ereseptdosing.extension:repeatingdosage.extension:timerange">
      <path value="Extension.extension.extension.extension" />
      <sliceName value="timerange" />
      <max value="1" />
    </element>
    <element id="Extension.extension:ereseptdosing.extension:repeatingdosage.extension:timerange.url">
      <path value="Extension.extension.extension.extension.url" />
      <fixedString value="timerange" />
    </element>
    <element id="Extension.extension:ereseptdosing.extension:repeatingdosage.extension:accurate">
      <path value="Extension.extension.extension.extension" />
      <sliceName value="accurate" />
      <min value="1" />
      <max value="1" />
    </element>
    <element id="Extension.extension:ereseptdosing.extension:repeatingdosage.extension:accurate.url">
      <path value="Extension.extension.extension.extension.url" />
      <fixedString value="accurate" />
    </element>
    <element id="Extension.extension:ereseptdosing.extension:repeatingdosage.extension:dosingsequence">
      <path value="Extension.extension.extension.extension" />
      <sliceName value="dosingsequence" />
      <max value="1" />
    </element>
    <element id="Extension.extension:ereseptdosing.extension:repeatingdosage.extension:dosingsequence.extension">
      <path value="Extension.extension.extension.extension.extension" />
      <slicing>
        <discriminator>
          <type value="value" />
          <path value="url" />
        </discriminator>
        <rules value="open" />
      </slicing>
    </element>
    <element id="Extension.extension:ereseptdosing.extension:repeatingdosage.extension:dosingsequence.extension:weekdays">
      <path value="Extension.extension.extension.extension.extension" />
      <sliceName value="weekdays" />
    </element>
    <element id="Extension.extension:ereseptdosing.extension:repeatingdosage.extension:dosingsequence.extension:weekdays.url">
      <path value="Extension.extension.extension.extension.extension.url" />
      <fixedString value="weekdays" />
    </element>
    <element id="Extension.extension:ereseptdosing.extension:repeatingdosage.extension:dosingsequence.extension:dayson">
      <path value="Extension.extension.extension.extension.extension" />
      <sliceName value="dayson" />
      <max value="1" />
    </element>
    <element id="Extension.extension:ereseptdosing.extension:repeatingdosage.extension:dosingsequence.extension:dayson.url">
      <path value="Extension.extension.extension.extension.extension.url" />
      <fixedString value="dayson" />
    </element>
    <element id="Extension.extension:ereseptdosing.extension:repeatingdosage.extension:dosingsequence.extension:daysoff">
      <path value="Extension.extension.extension.extension.extension" />
      <sliceName value="daysoff" />
      <max value="1" />
    </element>
    <element id="Extension.extension:ereseptdosing.extension:repeatingdosage.extension:dosingsequence.extension:daysoff.url">
      <path value="Extension.extension.extension.extension.extension.url" />
      <fixedString value="daysoff" />
    </element>
    <element id="Extension.extension:ereseptdosing.extension:repeatingdosage.extension:dosingsequence.url">
      <path value="Extension.extension.extension.extension.url" />
      <fixedString value="dosingsequence" />
    </element>
    <element id="Extension.extension:ereseptdosing.extension:repeatingdosage.extension:dosingsequence.value[x]">
      <path value="Extension.extension.extension.extension.value[x]" />
      <max value="0" />
    </element>
    <element id="Extension.extension:ereseptdosing.extension:repeatingdosage.url">
      <path value="Extension.extension.extension.url" />
      <fixedString value="repeatingdosage" />
    </element>
    <element id="Extension.extension:ereseptdosing.extension:repeatingdosage.value[x]">
      <path value="Extension.extension.extension.value[x]" />
      <max value="0" />
    </element>
    <element id="Extension.extension:ereseptdosing.url">
      <path value="Extension.extension.url" />
      <fixedString value="ereseptdosing" />
    </element>
    <element id="Extension.extension:ereseptdosing.value[x]">
      <path value="Extension.extension.value[x]" />
      <max value="0" />
    </element>
    <element id="Extension.url">
      <path value="Extension.url" />
      <fixedString value="http://ehelse.no/fhir/StructureDefinition/sfm-reseptamendment" />
    </element>
    <element id="Extension.value[x]">
      <path value="Extension.value[x]" />
      <max value="0" />
    </element>
  </differential>
</StructureDefinition>